tiles/__init__.py
tiles/__main__.py
tiles/alg/TILES.py
tiles/alg/__init__.py
tiles/alg/eTILES.py
tiles-1.0.4.dist-info/DESCRIPTION.rst
tiles-1.0.4.dist-info/METADATA
tiles-1.0.4.dist-info/RECORD
tiles-1.0.4.dist-info/WHEEL
tiles-1.0.4.dist-info/metadata.json
tiles-1.0.4.dist-info/top_level.txt
