Metadata-Version: 2.0
Name: tiles
Version: 1.0.4
Summary: Dynamic Community Discovery algorithm
Home-page: https://github.com/GiulioRossetti/TILES
Author: Giulio Rossetti
Author-email: giulio.rossetti@gmail.com
License: BSD-2-Clause
Keywords: complex-networks,dynamic community discovery,dynamic networks
Platform: UNKNOWN
Classifier: Development Status :: 5 - Production/Stable
Classifier: Intended Audience :: Developers
Classifier: Topic :: Software Development :: Build Tools
Classifier: License :: OSI Approved :: BSD License
Classifier: Operating System :: OS Independent
Classifier: Programming Language :: Python
Classifier: Programming Language :: Python :: 2.7
Classifier: Programming Language :: Python :: 3
Requires-Dist: future
Requires-Dist: networkx
